llamea/__init__.py
llamea/llamea.py
llamea/llm.py
llamea/loggers.py
llamea/solution.py
llamea/utils.py
llamea/bbobalgs/ERADS_QuantumFluxUltraRefined.py
llamea/bbobalgs/__init__.py
llamea_lite-1.1.10.dist-info/METADATA
llamea_lite-1.1.10.dist-info/WHEEL
llamea_lite-1.1.10.dist-info/licenses/LICENSE
llamea_lite-1.1.10.dist-info/RECORD
