Metadata-Version: 2.4
Name: llamea-lite
Version: 1.1.10
Summary: LLaMEA without bundled LLM or HPO dependencies
Project-URL: Homepage, https://github.com/XAI-liacs/LLaMEA
Project-URL: Repository, https://github.com/XAI-liacs/LLaMEA
Author-email: Niki van Stein <n.van.stein@liacs.leidenuniv.nl>
License-Expression: MIT
License-File: LICENSE
Requires-Python: <4,>=3.11
Requires-Dist: joblib<2,>=1.4.2
Requires-Dist: jsonlines<5,>=4.0.0
Requires-Dist: numpy<3,>=2
Requires-Dist: ollama<1,>=0.5.3
Requires-Dist: tqdm<5,>=4.66.4
